{
	"$schema" : "https://aka.ms/winget-packages.schema.2.0.json",
	"CreationDate" : "2021-08-21T16:07:47.223-00:00",
	"Sources" : 
	[
		{
			"Packages" : 
			[
				{
					"PackageIdentifier" : "Microsoft.VisualStudio.2019.BuildTools"
				},
				{
					"PackageIdentifier" : "Discord.Discord"
				},
				{
					"PackageIdentifier" : "Git.Git"
				},
				{
					"PackageIdentifier" : "GnuPG.GnuPG"
				},
				{
					"PackageIdentifier" : "Google.Chrome"
				},
				{
					"PackageIdentifier" : "GnuPG.Gpg4win"
				},
				{
					"PackageIdentifier" : "Microsoft.Edge"
				},
				{
					"PackageIdentifier" : "Microsoft.EdgeWebView2Runtime"
				},
				{
					"PackageIdentifier" : "Microsoft.WindowsTerminal"
				},
				{
					"PackageIdentifier" : "Mozilla.Thunderbird"
				},
				{
					"PackageIdentifier" : "Spotify.Spotify"
				},
				{
					"PackageIdentifier" : "Valve.Steam"
				},
				{
					"PackageIdentifier" : "Ubisoft.Connect"
				},
				{
					"PackageIdentifier" : "VideoLAN.VLC"
				},
				{
					"PackageIdentifier" : "RARLab.WinRAR"
				},
				{
					"PackageIdentifier" : "Balena.Etcher"
				},
				{
					"PackageIdentifier" : "Python.Python.3"
				},
				{
					"PackageIdentifier" : "Microsoft.VC++2010Redist-x64"
				},
				{
					"PackageIdentifier" : "Microsoft.VC++2012Redist-x86"
				},
				{
					"PackageIdentifier" : "Telegram.TelegramDesktop"
				},
				{
					"PackageIdentifier" : "EpicGames.EpicGamesLauncher"
				},
				{
					"PackageIdentifier" : "OpenJS.NodeJS"
				},
				{
					"PackageIdentifier" : "Transmission.Transmission"
				},
				{
					"PackageIdentifier" : "Google.BackupAndSync"
				},
				{
					"PackageIdentifier" : "Microsoft.UpdateAssistant"
				},
				{
					"PackageIdentifier" : "Microsoft.VisualStudioCode"
				},
				{
					"PackageIdentifier" : "Microsoft.VC++2010Redist-x86"
				},
				{
					"PackageIdentifier" : "Microsoft.VC++2012Redist-x64"
				}
			],
			"SourceDetails" : 
			{
				"Argument" : "https://winget.azureedge.net/cache",
				"Identifier" : "Microsoft.Winget.Source_8wekyb3d8bbwe",
				"Name" : "winget",
				"Type" : "Microsoft.PreIndexed.Package"
			}
		},
		{
			"Packages" : 
			[
				{
					"PackageIdentifier" : "Microsoft.Whiteboard"
				}
			],
			"SourceDetails" : 
			{
				"Argument" : "https://winget.azureedge.net/msstore",
				"Identifier" : "Microsoft.Winget.MSStore.Source_8wekyb3d8bbwe",
				"Name" : "msstore",
				"Type" : "Microsoft.PreIndexed.Package"
			}
		}
	],
	"WinGetVersion" : "1.0.11692"
}